datasay/__init__.py
datasay/core.py
datasay-0.2.1.dist-info/licenses/LICENSE
datasay-0.2.1.dist-info/METADATA
datasay-0.2.1.dist-info/WHEEL
datasay-0.2.1.dist-info/top_level.txt
datasay-0.2.1.dist-info/RECORD
