Metadata-Version: 2.4
Name: datasay
Version: 0.2.1
Summary: Human-readable explanations for numeric data
Author: Ajmal S
Requires-Python: >=3.7
License-File: LICENSE
Dynamic: author
Dynamic: license-file
Dynamic: requires-python
Dynamic: summary
